{
  "model": "GEEKOM Mini Air12 Lite",
  "description": {
    "en": "The GEEKOM Mini Air12 Lite is a compact and efficient mini PC powered by the 12th Gen Intel® N100 processor, featuring Intel® UHD Graphics. Designed for daily tasks, it offers 8GB DDR4 3200 MT/s RAM (expandable to 16GB) and 256GB PCIe 3.0 NVMe SSD storage (upgradable to 1TB). With WiFi 5, Bluetooth 5.1, and dual 4K display support via HDMI 2.0 and DP 1.4, it’s ideal for home, office, or light multimedia use. Its ultra-compact design (135.5 × 115.5 × 34.5 mm) includes multiple ports like USB 3.2, Ethernet, and audio jacks. Preinstalled with Windows 11 Pro, it combines portability with reliable performance.",
    "es": "El GEEKOM Mini Air12 Lite es un mini PC compacto y eficiente con el procesador Intel® N100 de 12ª generación y gráficos Intel® UHD. Diseñado para tareas diarias, incluye 8 GB de RAM DDR4 3200 MT/s (ampliable a 16 GB) y almacenamiento SSD NVMe PCIe 3.0 de 256 GB (hasta 1 TB). Con WiFi 5, Bluetooth 5.1 y soporte para dos pantallas 4K mediante HDMI 2.0 y DP 1.4, es ideal para hogar, oficina o multimedia ligera. Su diseño ultracompacto (135,5 × 115,5 × 34,5 mm) incluye múltiples puertos como USB 3.2, Ethernet y jack de audio. Viene con Windows 11 Pro preinstalado, combinando portabilidad y rendimiento."
  },
  "mainImgUrls": null,
  "portsImgUrls": null,
  "cpu": {
    "brand": "Intel",
    "model": "N100",
    "cores": 4,
    "threads": 4,
    "baseClockGHz": null,
    "boostClockGHz": 3.4,
    "cache": {
      "type": null,
      "capacityMB": null
    }
  },
  "variants": [
    {
      "ram": {
        "capacityGB": 8,
        "type": "DDR4"
      },
      "storage": {
        "type": "PCIe 3.0 NVMe",
        "capacityGB": 256
      },
      "oferts": [
        {
          "url": null,
          "priceUsd": null,
          "warrantyYears": 3
        }
      ]
    }
  ],
  "maxRAMCapacityGB": 16,
  "maxStorageCapacityGB": 1000,
  "graphics": {
    "integrated": true,
    "brand": "Intel",
    "model": "UHD Graphics",
    "frequencyMHz": null,
    "graphicCoresCU": null,
    "maxTOPS": null,
    "displayPorts": {
      "thunderbolt": {
        "amount": null,
        "type": null
      },
      "dp": {
        "amount": 1,
        "type": "1.4"
      },
      "hdmi": {
        "amount": 1,
        "type": "2.0"
      },
      "usb4": {
        "amount": null,
        "type": null
      }
    }
  },
  "ports": {
    "usb4": null,
    "usb3": 4,
    "usb2": 2,
    "usbC": null,
    "ethernet": 1,
    "audioJack": true,
    "sdCardReader": null
  },
  "builtinMicrophone": null,
  "builtinSpeakers": null,
  "supportExternalDiscreteGraphicsCard": null,
  "connectivity": {
    "wifi": "WiFi 5",
    "bluetooth": "5.1"
  },
  "dimensions": {
    "widthMm": 135.5,
    "heightMm": 115.5,
    "depthMm": 34.5,
    "volumeL": 0.54
  },
  "weightKg": 1,
  "powerConsumptionW": null,
  "releaseYear": null
}